grumpy/__init__.py
grumpy_arrays-0.1.3.dist-info/METADATA
grumpy_arrays-0.1.3.dist-info/WHEEL
grumpy_arrays-0.1.3.dist-info/top_level.txt
grumpy_arrays-0.1.3.dist-info/RECORD
