Metadata-Version: 2.4
Name: grumpy-arrays
Version: 0.1.3
Summary: A minimal example Python package.
Author-email: Your Name <you@example.com>
Project-URL: Homepage, https://github.com/Imaginary-Biolabs/grumpy
Project-URL: Repository, https://github.com/Imaginary-Biolabs/grumpy
Project-URL: Issues, https://github.com/Imaginary-Biolabs/grumpy/issues
Keywords: example,package
Classifier: Programming Language :: Python :: 3
Classifier: Operating System :: OS Independent
Requires-Python: >=3.9
